labview_fpga_hdl_tools/__init__.py
labview_fpga_hdl_tools/__main__.py
labview_fpga_hdl_tools/common.py
labview_fpga_hdl_tools/create_lvbitx.py
labview_fpga_hdl_tools/create_vivado_project.py
labview_fpga_hdl_tools/gen_labview_target_plugin.py
labview_fpga_hdl_tools/get_window_netlist.py
labview_fpga_hdl_tools/install_dependencies.py
labview_fpga_hdl_tools/install_labview_target_plugin.py
labview_fpga_hdl_tools/launch_vivado.py
labview_fpga_hdl_tools/migrate_clip.py
labview_fpga_hdl_tools-0.1.8.dist-info/LICENSE
labview_fpga_hdl_tools-0.1.8.dist-info/METADATA
labview_fpga_hdl_tools-0.1.8.dist-info/WHEEL
labview_fpga_hdl_tools-0.1.8.dist-info/entry_points.txt
labview_fpga_hdl_tools-0.1.8.dist-info/RECORD
